README.txt
setup.py
py_ace.egg-info/PKG-INFO
py_ace.egg-info/SOURCES.txt
py_ace.egg-info/dependency_links.txt
py_ace.egg-info/requires.txt
py_ace.egg-info/top_level.txt
pyace/__init__.py
pyace/cython_setup.py