Metadata-Version: 1.1
Name: py-ace
Version: 0.0.3
Summary: make all python script as c extention with cython
Home-page: UNKNOWN
Author: MaxiL
Author-email: maxil@interserv.com.tw
License: UNKNOWN
Download-URL: https://github.com/maxi119/py-ace
Platform: UNKNOWN
Classifier: Development Status :: 1 - Planning
Classifier: Intended Audience :: Developers
Classifier: License :: OSI Approved :: Python Software Foundation License
Classifier: Programming Language :: Python
Classifier: Topic :: Utilities
Classifier: Topic :: Security
Classifier: Topic :: Software Development :: Libraries :: Python Modules
